README.md
setup.py
vizme/__init__.py
vizme/__main__.py
vizme/utils.py
vizme/vizme.py
vizme.egg-info/PKG-INFO
vizme.egg-info/SOURCES.txt
vizme.egg-info/dependency_links.txt
vizme.egg-info/entry_points.txt
vizme.egg-info/requires.txt
vizme.egg-info/top_level.txt
vizme/palettes/__init__.py
vizme/palettes/dawnbringer.py
vizme/palettes/greyscale.py
vizme/palettes/pixd.py
vizme/palettes/test_palette_file.py