Metadata-Version: 2.1
Name: vizme
Version: 0.1.3
Summary: A simple python-based command-line utility to to visualize random blobs of data.
Home-page: https://github.com/0x3a/vizme
Author: Yonathan Klijnsma
Author-email: admin@0x3a.com
License: UNKNOWN
Platform: UNKNOWN
Requires-Python: >=3
